allpurpose/__init__.py
allpurpose/cli.py
allpurpose/crypto.py
allpurpose/file.py
allpurpose/image.py
allpurpose/image_store.py
allpurpose/json.py
allpurpose/module.py
allpurpose/serializer.py
allpurpose/string.py
allpurpose-0.2.dist-info/LICENSE
allpurpose-0.2.dist-info/METADATA
allpurpose-0.2.dist-info/WHEEL
allpurpose-0.2.dist-info/top_level.txt
allpurpose-0.2.dist-info/RECORD
