Metadata-Version: 2.1
Name: allpurpose
Version: 0.2
Summary: UNKNOWN
Home-page: UNKNOWN
License: UNKNOWN
Platform: UNKNOWN
License-File: LICENSE
Requires-Dist: Pillow ==10.1.0
